test/__init__.py
test/setup.py
recommendation9-0.1.dist-info/METADATA
recommendation9-0.1.dist-info/WHEEL
recommendation9-0.1.dist-info/top_level.txt
recommendation9-0.1.dist-info/RECORD
